caddypy/__init__.py
caddypy/caddy.py
caddypy-1.0.0.dist-info/LICENSE
caddypy-1.0.0.dist-info/METADATA
caddypy-1.0.0.dist-info/WHEEL
caddypy-1.0.0.dist-info/top_level.txt
caddypy-1.0.0.dist-info/RECORD
