Metadata-Version: 2.1
Name: caddypy
Version: 1.0.0
Summary: Python library for the Caddy server
Home-page: https://github.com/anuj9196/caddypy
Author: Anuj Sharma
Author-email: anujsharma9196@gmail.com
License: UNKNOWN
Platform: UNKNOWN
Classifier: Programming Language :: Python :: 3
Classifier: License :: OSI Approved :: MIT License
Classifier: Operating System :: OS Independent
Requires-Python: >=3.6
